date_parser/__init__.py
date_parser/parser.py
date_parser/settings.py
date_parser-0.3.dist-info/DESCRIPTION.rst
date_parser-0.3.dist-info/METADATA
date_parser-0.3.dist-info/RECORD
date_parser-0.3.dist-info/WHEEL
date_parser-0.3.dist-info/metadata.json
date_parser-0.3.dist-info/top_level.txt
