Metadata-Version: 2.0
Name: date-parser
Version: 0.3
Summary: Parse different date strings into YYYY-MM-DD format
Home-page: https://github.com/evyatarmeged/date-parser
Author: Evyatar Meged
Author-email: evyatarmeged@gmail.com
License: MIT
Keywords: date,parsing,strings
Platform: UNKNOWN
Classifier: Programming Language :: Python :: 3
Requires-Python: >=3
Requires-Dist: python-dateutil (>=2.6.0)
